4jawaly_sms/__init__.py
4jawaly_sms/client.py
4jawaly_sms/exceptions.py
sms4jawaly_sms/__init__.py
sms4jawaly_sms/models.py
sms4jawaly_sms/sms_gateway.py
sms4jawaly_sms-1.0.0.dist-info/METADATA
sms4jawaly_sms-1.0.0.dist-info/WHEEL
sms4jawaly_sms-1.0.0.dist-info/top_level.txt
sms4jawaly_sms-1.0.0.dist-info/RECORD
