Metadata-Version: 2.1
Name: sms4jawaly-sms
Version: 1.0.0
Summary: Python SDK for 4jawaly SMS Gateway
Home-page: https://github.com/4jawaly/sms-gateway-python
Author: 4jawaly
Author-email: support@4jawaly.com
Project-URL: Bug Reports, https://github.com/4jawaly/sms-gateway-python/issues
Project-URL: Source, https://github.com/4jawaly/sms-gateway-python
Keywords: sms,messaging,4jawaly,gateway
Classifier: Development Status :: 5 - Production/Stable
Classifier: Intended Audience :: Developers
Classifier: License :: OSI Approved :: MIT License
Classifier: Operating System :: OS Independent
Classifier: Programming Language :: Python :: 3
Classifier: Programming Language :: Python :: 3.7
Classifier: Programming Language :: Python :: 3.8
Classifier: Programming Language :: Python :: 3.9
Classifier: Programming Language :: Python :: 3.10
Classifier: Topic :: Software Development :: Libraries :: Python Modules
Classifier: Topic :: Communications :: Telephony
Requires-Python: >=3.7
Requires-Dist: requests >=2.25.0
Requires-Dist: pydantic >=1.8.0
